CKechengJiangyiChuanzhiSaodiSeng/README.md
CKechengJiangyiChuanzhiSaodiSeng/__init__.py
CKechengJiangyiChuanzhiSaodiSeng/__main__.py
CKechengJiangyiChuanzhiSaodiSeng/file.pdf
CKechengJiangyiChuanzhiSaodiSeng/index.html
c_kecheng_jiangyi_chuanzhi_saodi_seng-2024.3.2.0.dist-info/METADATA
c_kecheng_jiangyi_chuanzhi_saodi_seng-2024.3.2.0.dist-info/WHEEL
c_kecheng_jiangyi_chuanzhi_saodi_seng-2024.3.2.0.dist-info/entry_points.txt
c_kecheng_jiangyi_chuanzhi_saodi_seng-2024.3.2.0.dist-info/top_level.txt
c_kecheng_jiangyi_chuanzhi_saodi_seng-2024.3.2.0.dist-info/RECORD
